cyfunc
