Metadata-Version: 2.1
Name: cyfunc
Version: 0.1.4
Summary: UNKNOWN
Home-page: https://github.com/tillahoffmann/cyfunc
Author: Till Hoffmann
License: UNKNOWN
Platform: UNKNOWN
Provides-Extra: tests
